LICENSE
README.rst
TODO.rst
setup.py
serendipyty/__init__.py
serendipyty/version.py
serendipyty.egg-info/PKG-INFO
serendipyty.egg-info/SOURCES.txt
serendipyty.egg-info/dependency_links.txt
serendipyty.egg-info/not-zip-safe
serendipyty.egg-info/requires.txt
serendipyty.egg-info/top_level.txt
serendipyty/io/__init__.py
serendipyty/seismic/__init__.py
serendipyty/seismic/hpc/__init__.py
serendipyty/seismic/hpc/hpc.py
serendipyty/seismic/input/__init__.py
serendipyty/seismic/input/sources.py
serendipyty/seismic/input/wavelets.py
serendipyty/seismic/model/__init__.py
serendipyty/seismic/model/models.py
serendipyty/seismic/modelling/__init__.py
serendipyty/seismic/modelling/awe2d.c
serendipyty/seismic/modelling/awe2d.pyx
serendipyty/seismic/modelling/bcs.py
serendipyty/seismic/modelling/ebc_filippo.c
serendipyty/seismic/modelling/ebc_filippo.pyx
serendipyty/seismic/modelling/generate_pml_coeff.c
serendipyty/seismic/modelling/generate_pml_coeff.pxd
serendipyty/seismic/modelling/generate_pml_coeff.pyx
serendipyty/seismic/output/__init__.py
serendipyty/seismic/output/shotgathers.py
serendipyty/seismic/utils/__init__.py
serendipyty/seismic/utils/dispersion.py
serendipyty/seismic/utils/fd.py
serendipyty/seismic/utils/util.py
serendipyty/seismic/vis/__init__.py
serendipyty/seismic/vis/vis.py
serendipyty/vis/__init__.py
serendipyty/vis/vis.py