Metadata-Version: 1.2
Name: serendipyty
Version: 0.0.8
Summary: A Python library for learning and teaching Geophysics
Home-page: https://github.com/serendipyty/serendipyty
Author: Filippo Broggini
Author-email: filippo.broggini@erdw.ethz.ch
License: Apache License 2.0
Keywords: setuptools template example cython
Platform: Linux
Classifier: Development Status :: 1 - Planning
Classifier: Environment :: Console
Classifier: Intended Audience :: Developers
Classifier: Intended Audience :: Science/Research
Classifier: License :: OSI Approved :: Apache Software License
Classifier: Operating System :: POSIX :: Linux
Classifier: Programming Language :: Cython
Classifier: Programming Language :: Python
Classifier: Programming Language :: Python :: 3.4
Classifier: Topic :: Scientific/Engineering
Classifier: Topic :: Scientific/Engineering :: Mathematics
Classifier: Topic :: Software Development :: Libraries
Classifier: Topic :: Software Development :: Libraries :: Python Modules
Requires-Python: >=3.4
